macsanity/__init__.py
macsanity/cli.py
macsanity/macsanity.py
macsanity-1.0.1.dist-info/METADATA
macsanity-1.0.1.dist-info/WHEEL
macsanity-1.0.1.dist-info/entry_points.txt
macsanity-1.0.1.dist-info/top_level.txt
macsanity-1.0.1.dist-info/RECORD
