Metadata-Version: 2.4
Name: macsanity
Version: 1.0.1
Summary: A simple tool for formatting MAC addresses
Author: anython
